setup.py
Products/__init__.py
Products.SecureMaildropHost.egg-info/PKG-INFO
Products.SecureMaildropHost.egg-info/SOURCES.txt
Products.SecureMaildropHost.egg-info/dependency_links.txt
Products.SecureMaildropHost.egg-info/namespace_packages.txt
Products.SecureMaildropHost.egg-info/not-zip-safe
Products.SecureMaildropHost.egg-info/requires.txt
Products.SecureMaildropHost.egg-info/top_level.txt
Products/SecureMaildropHost/CHANGES.txt
Products/SecureMaildropHost/LICENSE.txt
Products/SecureMaildropHost/README.txt
Products/SecureMaildropHost/SecureMaildropHost.py
Products/SecureMaildropHost/__init__.py
Products/SecureMaildropHost/version.txt
Products/SecureMaildropHost/www/addSecureMaildropHost_form.dtml
Products/SecureMaildropHost/www/maildrop.gif
