Metadata-Version: 1.0
Name: Products.SecureMaildropHost
Version: 0.2
Summary: SecureMaildropHost marries SecureMailHost and MaildropHost, making this a drop-in replacement for SecureMailHost.
Home-page: http://plone.org/products/securemaildrophost
Author: Martijn Pieters
Author-email: info@jarn.com
License: UNKNOWN
Keywords: Zope
Platform: UNKNOWN
Classifier: Programming Language :: Python
Classifier: Framework :: Zope2
